circular_enterprise_apis/CEP_Account.py
circular_enterprise_apis/C_CERTIFICATE.py
circular_enterprise_apis/__init__.py
circular_enterprise_apis/helper.py
circular_enterprise_apis-1.0.1.dist-info/licenses/LICENSE
circular_enterprise_apis-1.0.1.dist-info/METADATA
circular_enterprise_apis-1.0.1.dist-info/WHEEL
circular_enterprise_apis-1.0.1.dist-info/top_level.txt
circular_enterprise_apis-1.0.1.dist-info/RECORD
