Metadata-Version: 2.4
Name: circular_enterprise_apis
Version: 1.0.1
Summary: Official Circular Protocol Enterprise APIs written in Python.
Home-page: https://github.com/circular-protocol/Python-Enterprise-APIs
Author: Danny De Novi
Author-email: Danny De Novi <dannydenovi@gmail.com>
Project-URL: Homepage, https://github.com/circular-protocol/Python-Enterprise-APIs
Project-URL: Bug Tracker, https://github.com/circular-protocol/Python-Enterprise-APIs/issues
Classifier: Programming Language :: Python :: 3
Classifier: License :: OSI Approved :: MIT License
Classifier: Operating System :: OS Independent
Requires-Python: >=3.8
License-File: LICENSE
Requires-Dist: requests>=2.32.3
Requires-Dist: ecdsa>=0.19.0
Dynamic: author
Dynamic: home-page
Dynamic: license-file
Dynamic: requires-python
